carbonai/__init__.py
carbonai/config.json
carbonai/data/ademe_energy_mix_by_country.csv
carbonai/magic_power_meter.py
carbonai/nvidia_power.py
carbonai/power_gadget.py
carbonai/power_meter.py
carbonai/utils.py
carbonai/version.py
carbonai-0.2.1.dist-info/LICENSE.txt
carbonai-0.2.1.dist-info/WHEEL
carbonai-0.2.1.dist-info/METADATA
carbonai-0.2.1.dist-info/RECORD
