Metadata-Version: 2.1
Name: carbonai
Version: 0.2.1
Summary: Monitor the power consumption of a function
Home-page: https://github.com/Capgemini-Invent-France/CarbonAI
License: MIT
Keywords: CarbonAI,energy usage,carbon footprint
Author: Capgemini Invent - Martin Chauvin, Francois Lemeille, Jordan Toh
Requires-Python: >=3.7.1,<4
Classifier: License :: OSI Approved :: MIT License
Classifier: Programming Language :: Python :: 3
Classifier: Programming Language :: Python :: 3.10
Classifier: Programming Language :: Python :: 3.8
Classifier: Programming Language :: Python :: 3.9
Requires-Dist: fuzzywuzzy (>=0.17.0)
Requires-Dist: ipython (>=7.12)
Requires-Dist: numpy (>=1.20.3)
Requires-Dist: pandas (>=1.0.5)
Requires-Dist: psutil
Requires-Dist: requests (>=2.20.1)
Project-URL: Documentation, https://capgemini-invent-france.github.io/CarbonAI/
Project-URL: Repository, https://github.com/Capgemini-Invent-France/CarbonAI
